{
  "characters": [
    {
      "id": "6367c33e64f544038d8d9582",
      "char_id": 1,
      "name": "Jimmy McGill",
      "birthday": "November 12, 1960",
      "occupation": [
        "Mailroom clerk at Hamlin, Hamlin & McGill",
        "Public Defense Attorney"
      ],
      "image": "https://cdn.discordapp.com/attachments/1167550007080124416/1169756570415026306/BCS_S6_Portrait_Jimmy.webp?ex=65568fb3&is=65441ab3&hm=1f8bd3baffd24308ca47e619c956a08d3f0a91aabbd8419c3d0a1adcf3e6648c&",
      "status": "Alive",
      "appearance": [1, 2, 3, 4, 5, 6],
      "firstAppearance": "Uno",
      "lastAppearance": "Saul Gone",
      "nickname": "Saul Goodman",
      "portrayed": "Bob Odenkirk"
    },
    {
      "id": "6367c3c464f544038d8d9586",
      "char_id": 2,
      "name": "Michael Ehrmantraut",
      "birthday": "Between 1940–1944",
      "occupation": [
        "Police Officer",
        "Private Investigator",
        "Ticket Booth Guard"
      ],
      "image": "https://cdn.discordapp.com/attachments/1167550007080124416/1169756636265578616/BCS_S6_Portrait_Mike.webp?ex=65568fc3&is=65441ac3&hm=aac72ff8dfc391b480f16954bcb250105f89c5d1c2fa8cc8c6a28e186b494e8e&",
      "status": "Deceased",
      "appearance": [1, 2, 3, 4, 5, 6],
      "firstAppearance": "Uno",
      "lastAppearance": "Saul Gone",
      "nickname": "Pop Pop",
      "portrayed": "Jonathan Banks"
    },
    {
      "id": "6367d781359b4d0aa083c84b",
      "char_id": 3,
      "name": "Kim Wexler",
      "birthday": "February 13, 1968",
      "occupation": [
        "Law student at University of New Mexico (former)",
        "Mailroom clerk at Hamlin, Hamlin & McGill (former)",
        "Associate at HHM (former)"
      ],
      "image": "https://cdn.discordapp.com/attachments/1167550007080124416/1169756583979397140/BCS_S6_Portrait_Kim.webp?ex=65568fb6&is=65441ab6&hm=ecc4a99599b0c277497e97b1cbb770fb157db4cfb580a7b7679ede9ed39fa665&",
      "status": "Alive",
      "appearance": [1, 2, 3, 4, 5, 6],
      "firstAppearance": "Uno",
      "lastAppearance": "Saul Gone",
      "portrayed": "Rhea Seehorn"
    },
    {
      "id": "6367d7d9480b60c0d323922f",
      "char_id": 4,
      "name": "Howard Hamlin",
      "birthday": "Mid or late 1960s",
      "occupation": ["Lawyer at Hamlin, Hamlin & McGill"],
      "image": "https://cdn.discordapp.com/attachments/1167550007080124416/1169756557060354180/BCS_S6_Portrait_Howard.webp?ex=65568fb0&is=65441ab0&hm=013b1ec60df754bef1498ce09f1978821261e336f2ac47c308567bbdc5b5319b&",
      "status": "Deceased",
      "appearance": [1, 2, 3, 4, 5, 6],
      "firstAppearance": "Uno",
      "lastAppearance": "Fund and Games",
      "nickname": "Howard",
      "portrayed": "Patrick Fabian"
    },
    {
      "id": "6367d869c2d4b8d865a0067b",
      "char_id": 5,
      "name": "Chuck McGill",
      "birthday": "1944",
      "occupation": ["Lawyer at Hamlin, Hamlin & McGill"],
      "image": "https://cdn.discordapp.com/attachments/1167550007080124416/1169756519559073822/BCS_S3_ChuckMcGill.webp?ex=65568fa7&is=65441aa7&hm=4f08489ca5059cf97670b878c021ce1e3ad2b778cd0b46d224baf1ec8f45fec0&",
      "status": "Deceased",
      "appearance": [1, 2, 3, 4, 6],
      "firstAppearance": "Uno",
      "lastAppearance": "Lantern",
      "nickname": "Chuck",
      "portrayed": "Michael McKean"
    },
    {
      "id": "6367d8b6c2d4b8d865a0067d",
      "char_id": 6,
      "name": "Eduardo Lalo Salamanca",
      "birthday": "1960",
      "occupation": ["Cartel Member", "Drug Lord"],
      "image": "https://cdn.discordapp.com/attachments/1167550007080124416/1169756609216520262/BCS_S6_Portrait_Lalo.webp?ex=65568fbc&is=65441abc&hm=9832bcc636824c54c30ef8bf6a3dc53dd9d1d6e99a1439c61c59e7c5537ceaaf&",
      "status": "Deceased",
      "appearance": [4, 5, 6],
      "firstAppearance": "Coushatta",
      "lastAppearance": "Point and Shoot",
      "nickname": "Lalo",
      "portrayed": "Tony Dalton"
    },
    {
      "id": "6367d8d4c2d4b8d865a0067f",
      "char_id": 7,
      "name": "Gustavo Fring",
      "birthday": "Late 1950s or early 1960s",
      "occupation": ["Drug Lord", "Los Pollos Hermanos CEO"],
      "image": "https://cdn.discordapp.com/attachments/1167550007080124416/1169756534952177815/BCS_S3_GusFringe.webp?ex=65568faa&is=65441aaa&hm=3e02d35f21425b6345fbeea1071e26c0382b77769b3ae6d12c598520cb3e9dd7&",
      "status": "Deceased",
      "appearance": [3, 4, 5, 6],
      "firstAppearance": "Witness",
      "lastAppearance": "Fun and Games",
      "nickname": "Gus",
      "portrayed": "Giancarlo Esposito"
    },
    {
      "id": "6367d915c2d4b8d865a00683",
      "char_id": 8,
      "name": "Hector Salamanca",
      "birthday": "1939",
      "occupation": ["Cartel Member", "Drug Lord"],
      "image": "https://cdn.discordapp.com/attachments/1167550007080124416/1169756695493361794/TioSalamanca.webp?ex=65568fd1&is=65441ad1&hm=fb9d46419fb88798ebb2c927b647549e082dc42aeb794e3690737cc42a468ce4&",
      "status": "Deceased",
      "appearance": [2, 3, 4, 5, 6],
      "firstAppearance": "Rebecca",
      "lastAppearance": "Fun and Games",
      "nickname": "Tio",
      "portrayed": "Mark Margolis"
    },
    {
      "id": "6367d9a6c2d4b8d865a00685",
      "char_id": 9,
      "name": "Stacey Ehrmantraut",
      "birthday": "Unknown",
      "occupation": ["Nursing/medicine"],
      "image": "https://cdn.discordapp.com/attachments/1167550007080124416/1169756694776119366/Stacey_S5.webp?ex=65568fd1&is=65441ad1&hm=4fd55b8d0c592bb480f16ebe6256a18f301c956916e58031b384541abe039171&",
      "status": "Alive",
      "appearance": [2, 3, 4, 5, 6],
      "firstAppearance": "Alpine Shepherd Boy",
      "lastAppearance": "Axe and Grind",
      "nickname": "Stace",
      "portrayed": "Kerry Condon"
    },
    {
      "id": "6367da33c2d4b8d865a00687",
      "char_id": 10,
      "name": "Kaylee Ehrmantraut",
      "birthday": "c. 1997",
      "occupation": ["Unknown"],
      "image": "https://cdn.discordapp.com/attachments/1167550007080124416/1169756637653913620/Kaylee_Ehrmantraut.webp?ex=65568fc3&is=65441ac3&hm=160afab760db846a739612229e3ec62d49d04fbfd91e0fad94e22a20224aebdd&",
      "status": "Alive",
      "appearance": [1, 2, 3, 4, 5, 6],
      "firstAppearance": "Five-O",
      "lastAppearance": "Axe and Grind",
      "nickname": "Unknown",
      "portrayed": "Kaija Roze Bales"
    },
    {
      "id": "6367daa9c2d4b8d865a00689",
      "char_id": 11,
      "name": "Paige Novick",
      "birthday": "Unknown",
      "occupation": ["Senior Counsel for Mesa Verde Bank & Trust"],
      "image": "https://cdn.discordapp.com/attachments/1167550007080124416/1169756693035503710/Paige_Novick.webp?ex=65568fd0&is=65441ad0&hm=4f2d85cf30e470e9d9896a67f160921203545b69570530696bb7b1f0c5b4632a&",
      "status": "Alive",
      "appearance": [2, 3, 4, 5],
      "firstAppearance": "Rebecca",
      "lastAppearance": "JMM",
      "nickname": "Unknown",
      "portrayed": "Cara Pifko"
    },
    {
      "id": "6367db28c2d4b8d865a0068b",
      "char_id": 12,
      "name": "Victor",
      "birthday": "c. 1974",
      "occupation": [
        "Member of the Los Pollos Hermanos security staff Henchman of Gustavo Fring"
      ],
      "image": "https://cdn.discordapp.com/attachments/1167550007080124416/1169756696923619348/Victor_2009.webp?ex=65568fd1&is=65441ad1&hm=a997c25f8d3e72639c7253fda6901e9538601fdba1af9c0cef1aa64be3c095db&",
      "status": "Deceased",
      "appearance": [3, 4, 5, 6],
      "firstAppearance": "Witness",
      "lastAppearance": "Point and Shoot",
      "nickname": "Unsub Bystander",
      "portrayed": "Jeremiah Bitsui"
    },
    {
      "id": "6367dba0c2d4b8d865a0068d",
      "char_id": 13,
      "name": "Richard I. Schweikart",
      "birthday": "c. 1974",
      "occupation": [
        "Co-founder of Schweikart & Cokely",
        "Attorney for Sandpiper Crossing"
      ],
      "image": "https://cdn.discordapp.com/attachments/1167550007080124416/1169756502869938236/BCS_407_Rich_Schweikart.webp?ex=65568fa3&is=65441aa3&hm=c77ad62ab8a622967433ec56d9c71c14edc9c6619882e75d041b902f7928eb55&",
      "status": "Alive",
      "appearance": [1, 2, 4, 5, 6],
      "firstAppearance": "RICO",
      "lastAppearance": "Fun and Games",
      "nickname": "Rick",
      "portrayed": "Dennis Boutsikaris"
    },
    {
      "id": "6368c88e90673c31dd71d49d",
      "char_id": 14,
      "name": "Marshall Dixon",
      "birthday": "c. 1982",
      "occupation": ["Student at University of New Mexico"],
      "image": "https://cdn.discordapp.com/attachments/1167550007080124416/1169756637221896262/Joey_S5.webp?ex=65568fc3&is=65441ac3&hm=e4ff6a968b9b8773b9981759a5303109c92710f99b91498300880fd660703195&",
      "status": "Alive",
      "appearance": [1, 2, 3, 4, 5, 6],
      "firstAppearance": "Hero",
      "lastAppearance": "Plan and Execution",
      "portrayed": "Josh Fadem"
    },
    {
      "id": "6368c8d990673c31dd71d4a0",
      "char_id": 15,
      "name": "Sound guy",
      "birthday": "Who the fuck knows?",
      "occupation": ["Student at University of New Mexico"],
      "image": "https://cdn.discordapp.com/attachments/1167550007080124416/1169756693933080697/Sound_Guy_S5.webp?ex=65568fd0&is=65441ad0&hm=9a3b9253a079b10aac1b986d61fd220cc81e97e5a64d2110b7fdf8a748fc9a2a&",
      "status": "Alive",
      "appearance": [1, 2, 3, 4, 5, 6],
      "firstAppearance": "Hero",
      "lastAppearance": "Plan and Execution",
      "portrayed": "Julian Bonfiglio"
    },
    {
      "id": "6368c93590673c31dd71d4a3",
      "char_id": 16,
      "name": "Kevin Wachtell",
      "birthday": "c. 1950",
      "occupation": ["CEO of Mesa Verde Bank and Trust"],
      "image": "https://cdn.discordapp.com/attachments/1167550007080124416/1169756691915604058/Kevin_wachtell_2002.webp?ex=65568fd0&is=65441ad0&hm=93cccae7ef5c79f1323fdcd269c771fd680393b22febce563966acfd6bbac39a&",
      "status": "Alive",
      "appearance": [1, 2, 3, 4, 5, 6],
      "firstAppearance": "Rebecca",
      "lastAppearance": "Wine and Roses",
      "portrayed": "Rex Linn"
    },
    {
      "id": "6368c97b90673c31dd71d4a6",
      "char_id": 17,
      "name": "Ernesto",
      "birthday": "Unknown",
      "occupation": ["Employee at Hamlin, Hamlin & McGill"],
      "img": "https://cdn.discordapp.com/attachments/1167550007080124416/1169756636693413938/Ernesto.webp?ex=65568fc3&is=65441ac3&hm=74a820f734e6e797335eeae96594b179893bffdbd401eae6be4fddeac6645366&",
      "status": "Alive",
      "appearance": [1, 2, 3, 4],
      "firstAppearance": "RICO",
      "lastAppearance": "Sunk Costs",
      "portrayed": "Brandon K. Hampton"
    },
    {
      "id": "6368ca0690673c31dd71d4ab",
      "char_id": 18,
      "name": "Arturo Colon",
      "birthday": "Unknown",
      "occupation": ["Cartel enforcer"],
      "image": "https://cdn.discordapp.com/attachments/1167550007080124416/1169756483706167338/Arturo_S3.webp?ex=65568f9e&is=65441a9e&hm=e8946169942aa99f2bc32f10b0a8d4a5224651fdf59cd0de385609addb4e2fc5&",
      "status": "Deceased",
      "appearance": [2, 3, 4],
      "firstAppearance": "Bali Ha'i",
      "lastAppearance": "Something Beautiful",
      "portrayed": "Vincent Fuentes"
    },
    {
      "id": "6368caa090673c31dd71d4ae",
      "char_id": 19,
      "name": "Tyrus Kitt",
      "birthday": "c. 1971",
      "occupation": [
        "Member of the Los Pollos Hermanos Security Staff",
        "Henchman of Gustavo Fring"
      ],
      "image": "https://cdn.discordapp.com/attachments/1167550007080124416/1169756696168648755/TyrusKitt.webp?ex=65568fd1&is=65441ad1&hm=bb15443d70b67e08ac960a88495a1c30267f823dd92376b699dd68ffa9aba7e7&",
      "status": "Deceased",
      "appearance": [4],
      "firstAppearance": "Sunk Costs",
      "lastAppearance": "Point and Shoot",
      "portrayed": "Ray Campbell"
    }
  ]
}
